<?xml version="1.0"?>
<method xmlns:xsi="http://www.w3.org/2001/XMLSchema-instance" xmlns:xsd="http://www.w3.org/2001/XMLSchema" xsi:type="OrmOtherMethod" id="d96602e0-f2f5-4414-ae48-821ba970f243" lastModifiedUtc="2013-11-21T01:49:31.530136Z" name="QFButton_OnClick" methodType="Other" actionType="None" returnMode="None" isInstance="false" containerName="InsertComplaint">
  <extendedMetaData />
  <ExtendedPropertiesCollection>
    <extendee type="Sage.Platform.Orm.Entities.OrmOtherMethod" />
  </ExtendedPropertiesCollection>
  <parameter>
    <OrmEntityMethodParam id="0befcfea-f328-4423-a34e-4705b452b99b" paramName="form" sequence="0" paramType="IInsertComplaint" />
    <OrmEntityMethodParam id="91660e0e-715d-4e57-b7e6-3f65de0366da" paramName="args" sequence="0" paramType="EventArgs" />
  </parameter>
  <preExecuteTargets />
  <methodTargets />
  <postExecuteTargets />
  <postFlushTargets />
</method>