<?xml version="1.0"?>
<method xmlns:xsi="http://www.w3.org/2001/XMLSchema-instance" xmlns:xsd="http://www.w3.org/2001/XMLSchema" id="03976db8-3694-46ce-a493-f0254a6f33d7" lastModifiedUtc="2013-12-19T00:52:05.5104402Z" name="OnCreate" methodType="CrudEvent" actionType="None" returnMode="None">
  <extendedMetaData />
  <ExtendedPropertiesCollection>
    <extendee type="Sage.Platform.Orm.Entities.OrmEntityMethod" />
  </ExtendedPropertiesCollection>
  <parameter />
  <preExecuteTargets />
  <methodTargets>
    <methodTarget id="00352a33-fe17-4121-9e71-85971273029a" lastModifiedUtc="2013-12-19T00:52:04.5253839Z" targetType="Sage.Platform.Orm.DefaultCRUDEventHandler, Sage.Platform" targetMethod="OnCreate" active="true">
      <ExtendedPropertiesCollection>
        <extendee type="Sage.Platform.Orm.Entities.OrmMethodTarget" />
      </ExtendedPropertiesCollection>
    </methodTarget>
  </methodTargets>
  <postExecuteTargets />
  <postFlushTargets />
</method>