<?xml version="1.0"?>
<relationship xmlns:xsi="http://www.w3.org/2001/XMLSchema-instance" xmlns:xsd="http://www.w3.org/2001/XMLSchema" id="a1afb93a-19c5-4af2-b6b3-cf0a8c1a7a3a" lastModifiedUtc="2013-12-22T05:44:32.6152363Z" parentEntityId="ebfd715e-2b2f-4e5e-8c6d-cfc0d9b4ae52" childEntityId="e7a70408-03cb-4667-890b-39de33fb739b">
  <extendedMetaData />
  <ExtendedPropertiesCollection>
    <extendee type="Sage.Platform.Orm.Entities.OrmRelationship" />
  </ExtendedPropertiesCollection>
  <parentProperty id="09d92cf2-a241-43ed-b3fa-ef9504dd6065" lastModifiedUtc="2013-12-22T05:44:29.7680734Z" name="CallsEndCustomer" audited="false">
    <ExtendedPropertiesCollection>
      <extendee type="Sage.Platform.Orm.Entities.OrmRelationProperty">
        <extender guid="ae60621d-9d91-3d9a-b9fb-eb6c8be12131">
          <OrmEntityPropertySDataExtension generate="true" />
        </extender>
      </extendee>
    </ExtendedPropertiesCollection>
    <SystemDataType guid="2f770d03-c93c-4605-8ae8-7cdae04830d7">
      <RelationshipDataType />
    </SystemDataType>
  </parentProperty>
  <childProperty id="bd4ba7d1-a90d-4992-b20f-845cae8a71f0" lastModifiedUtc="2013-12-22T05:45:23.4721451Z" name="EndCustomers" audited="false">
    <ExtendedPropertiesCollection>
      <extendee type="Sage.Platform.Orm.Entities.OrmRelationProperty">
        <extender guid="ae60621d-9d91-3d9a-b9fb-eb6c8be12131">
          <OrmEntityPropertySDataExtension generate="true" />
        </extender>
      </extendee>
    </ExtendedPropertiesCollection>
    <SystemDataType guid="2f770d03-c93c-4605-8ae8-7cdae04830d7">
      <RelationshipDataType />
    </SystemDataType>
  </childProperty>
  <column>
    <OrmRelationshipColumn id="4b1a7418-beb2-47cf-9ebb-12324ee19b65" parentPropertyId="b24f58be-dd73-441a-a479-00e5f517b9e7" childPropertyId="c7ebe12c-a748-41ee-895a-3edee93f424a" ordinal="0" />
  </column>
</relationship>