<?xml version="1.0"?>
<entity xmlns:xsi="http://www.w3.org/2001/XMLSchema-instance" xmlns:xsd="http://www.w3.org/2001/XMLSchema" id="ac44226f-ffdc-45c7-878e-79d8321b1e14" lastModifiedUtc="2013-10-19T06:32:59.9338617Z" manageSchema="true" tableName="HOLIDAY" name="Holiday" displayPropertyId="4bb74ecd-f9fd-489a-9b11-a2fad6feffa6" isExtension="false" audited="false" smallImage="[Localization!Global_Images:Calendar_16x16]" largeImage="[Localization!Global_Images:Calendar_24x24]" onBeforeInsertMethodId="3a745d63-b7f5-437d-b7e6-26be9c622e45" onAfterInsertMethodId="317121e5-66d9-475f-8e40-35f4e30d181f" onBeforeUpdateMethodId="8c367b80-52bf-4799-880f-90561ef7d10d" onAfterUpdateMethodId="8e2c95d5-81d0-4789-a995-04355d693afc" onBeforeDeleteMethodId="9ca0b75d-1f43-4326-9d2f-fa60113339e4" onAfterDeleteMethodId="b258f060-0b4b-4430-aa68-e78ae0550ef5" onCreateId="9f326004-ec9d-4cf7-ba15-cbe95de460f1">
  <extendedMetaData />
  <ExtendedPropertiesCollection>
    <extendee type="Sage.Platform.Orm.Entities.OrmEntity">
      <extender guid="1589723d-0536-4bf3-bdd7-3f6f7fe165d0">
        <OrmEntityMetadataExtension>
          <StringExpression>${HeaderName}</StringExpression>
          <IsHistoryTable>false</IsHistoryTable>
        </OrmEntityMetadataExtension>
      </extender>
      <extender guid="76aa0e24-2c8f-3b71-a1f9-ca6db3db4459">
        <OrmEntitySDataExtension generateFeed="true" pathName="holidays" lastUpdatedPropertyId="c59b7f74-0615-4056-9bd0-e7914d7b9389" canPost="true" canPut="true" canDelete="true" />
      </extender>
    </extendee>
  </ExtendedPropertiesCollection>
  <keyProperties>
    <keyReference id="20a2ff6b-4154-4095-ad97-c0d09ef9d29a" ordinalPosition="0" />
  </keyProperties>
  <properties>
    <property xsi:type="OrmFieldProperty" id="20a2ff6b-4154-4095-ad97-c0d09ef9d29a" lastModifiedUtc="2013-10-17T09:18:06.0341009Z" name="HolidayId" audited="false" isNullable="false" columnName="HOLIDAYID" maxLength="12" precision="0" scale="0" ordinal="0" isReadOnly="false">
      <ExtendedPropertiesCollection>
        <extendee type="Sage.Platform.Orm.Entities.OrmFieldProperty">
          <extender guid="ae60621d-9d91-3d9a-b9fb-eb6c8be12131">
            <OrmEntityPropertySDataExtension generate="true" />
          </extender>
        </extendee>
      </ExtendedPropertiesCollection>
      <SystemDataType guid="30053f5a-8d40-4db1-b185-1e4128eb26cc">
        <StandardIdDataType />
      </SystemDataType>
    </property>
    <property xsi:type="OrmFieldProperty" id="32e4fc09-9c09-4c52-8dd2-eb6b8695b0ff" lastModifiedUtc="2013-10-17T09:18:06.0497009Z" name="CreateUser" audited="false" columnName="CREATEUSER" maxLength="12" precision="0" scale="0" ordinal="1" isReadOnly="false">
      <ExtendedPropertiesCollection>
        <extendee type="Sage.Platform.Orm.Entities.OrmFieldProperty">
          <extender guid="ae60621d-9d91-3d9a-b9fb-eb6c8be12131">
            <OrmEntityPropertySDataExtension generate="true" />
          </extender>
        </extendee>
      </ExtendedPropertiesCollection>
      <SystemDataType guid="30053f5a-8d40-4db1-b185-1e4128eb26cc">
        <StandardIdDataType />
      </SystemDataType>
    </property>
    <property xsi:type="OrmFieldProperty" id="8e0434ce-af7c-4e8b-beaf-84b9504dfe47" lastModifiedUtc="2013-10-17T09:18:06.0497009Z" name="CreateDate" audited="false" columnName="CREATEDATE" maxLength="0" precision="0" scale="0" ordinal="2" isReadOnly="false">
      <ExtendedPropertiesCollection>
        <extendee type="Sage.Platform.Orm.Entities.OrmFieldProperty">
          <extender guid="ae60621d-9d91-3d9a-b9fb-eb6c8be12131">
            <OrmEntityPropertySDataExtension generate="true" />
          </extender>
        </extendee>
      </ExtendedPropertiesCollection>
      <SystemDataType guid="1f08f2eb-87c8-443b-a7c2-a51f590923f5">
        <DateTimeDataType />
      </SystemDataType>
    </property>
    <property xsi:type="OrmFieldProperty" id="90f23d91-7e9f-4de3-8d07-6b843e3e558b" lastModifiedUtc="2013-10-17T09:18:06.0653009Z" name="ModifyUser" audited="false" columnName="MODIFYUSER" maxLength="12" precision="0" scale="0" ordinal="3" isReadOnly="false">
      <ExtendedPropertiesCollection>
        <extendee type="Sage.Platform.Orm.Entities.OrmFieldProperty">
          <extender guid="ae60621d-9d91-3d9a-b9fb-eb6c8be12131">
            <OrmEntityPropertySDataExtension generate="true" />
          </extender>
        </extendee>
      </ExtendedPropertiesCollection>
      <SystemDataType guid="30053f5a-8d40-4db1-b185-1e4128eb26cc">
        <StandardIdDataType />
      </SystemDataType>
    </property>
    <property xsi:type="OrmFieldProperty" id="c59b7f74-0615-4056-9bd0-e7914d7b9389" lastModifiedUtc="2013-10-17T09:18:06.0653009Z" name="ModifyDate" audited="false" columnName="MODIFYDATE" maxLength="0" precision="0" scale="0" ordinal="4" isReadOnly="false">
      <ExtendedPropertiesCollection>
        <extendee type="Sage.Platform.Orm.Entities.OrmFieldProperty">
          <extender guid="ae60621d-9d91-3d9a-b9fb-eb6c8be12131">
            <OrmEntityPropertySDataExtension generate="true" />
          </extender>
        </extendee>
      </ExtendedPropertiesCollection>
      <SystemDataType guid="1f08f2eb-87c8-443b-a7c2-a51f590923f5">
        <DateTimeDataType />
      </SystemDataType>
    </property>
    <property xsi:type="OrmFieldProperty" id="4afc5064-edb6-4a6b-9885-cdd6b494670d" lastModifiedUtc="2013-10-17T09:18:06.0653009Z" name="BranchId" audited="false" columnName="BRANCHID" maxLength="12" precision="0" scale="0" ordinal="5" isReadOnly="false">
      <ExtendedPropertiesCollection>
        <extendee type="Sage.Platform.Orm.Entities.OrmFieldProperty">
          <extender guid="ae60621d-9d91-3d9a-b9fb-eb6c8be12131">
            <OrmEntityPropertySDataExtension generate="true" />
          </extender>
        </extendee>
      </ExtendedPropertiesCollection>
      <SystemDataType guid="30053f5a-8d40-4db1-b185-1e4128eb26cc">
        <StandardIdDataType />
      </SystemDataType>
    </property>
    <property xsi:type="OrmFieldProperty" id="4bb74ecd-f9fd-489a-9b11-a2fad6feffa6" lastModifiedUtc="2013-10-19T06:32:59.9338617Z" name="HeaderName" audited="false" columnName="HEADERNAME" maxLength="64" precision="0" scale="0" ordinal="6" isReadOnly="false">
      <ExtendedPropertiesCollection>
        <extendee type="Sage.Platform.Orm.Entities.OrmFieldProperty">
          <extender guid="ae60621d-9d91-3d9a-b9fb-eb6c8be12131">
            <OrmEntityPropertySDataExtension generate="true" />
          </extender>
        </extendee>
      </ExtendedPropertiesCollection>
      <SystemDataType guid="b71918bf-fac1-4b62-9ed5-0b0294bc9900">
        <PickListDataType>
          <ValueStoredAsText>true</ValueStoredAsText>
          <AllowMultiples>false</AllowMultiples>
          <MustExistInList>true</MustExistInList>
          <NoneEditable>false</NoneEditable>
          <AlphaSort>false</AlphaSort>
          <Length>64</Length>
        </PickListDataType>
      </SystemDataType>
    </property>
    <property xsi:type="OrmFieldProperty" id="e42aad44-d56d-4e99-9240-610b59abe50f" lastModifiedUtc="2013-10-17T09:18:06.0809009Z" name="SeccodeId" audited="false" include="false" columnName="SECCODEID" maxLength="12" precision="0" scale="0" ordinal="7" isReadOnly="false">
      <ExtendedPropertiesCollection>
        <extendee type="Sage.Platform.Orm.Entities.OrmFieldProperty">
          <extender guid="ae60621d-9d91-3d9a-b9fb-eb6c8be12131">
            <OrmEntityPropertySDataExtension generate="true" />
          </extender>
        </extendee>
      </ExtendedPropertiesCollection>
      <SystemDataType guid="30053f5a-8d40-4db1-b185-1e4128eb26cc">
        <StandardIdDataType />
      </SystemDataType>
    </property>
  </properties>
</entity>